markdown_obsidian_callouts/__init__.py
markdown_obsidian_callouts/obsidian_callouts.py
markdown_obsidian_callouts/py.typed
markdown_obsidian_callouts-0.1.1.dist-info/LICENSE.md
markdown_obsidian_callouts-0.1.1.dist-info/METADATA
markdown_obsidian_callouts-0.1.1.dist-info/WHEEL
markdown_obsidian_callouts-0.1.1.dist-info/entry_points.txt
markdown_obsidian_callouts-0.1.1.dist-info/top_level.txt
markdown_obsidian_callouts-0.1.1.dist-info/RECORD
