Metadata-Version: 2.2
Name: markdown-obsidian-callouts
Version: 0.1.1
Summary: MarkDown extension: a classier syntax for admonitions
Author-email: Lex Toumbourou <lextoumbourou@gmail.com>
License: MIT License
Project-URL: Documentation, https://github.com/lextoumbourou/markdown-obsidian-callouts
Project-URL: Source, https://github.com/lextoumbourou/markdown-obsidian-callouts
Keywords: markdown,extensions
Classifier: Development Status :: 4 - Beta
Classifier: Environment :: Web Environment
Classifier: Intended Audience :: Information Technology
Classifier: License :: OSI Approved :: MIT License
Classifier: Operating System :: OS Independent
Classifier: Programming Language :: Python :: 3.9
Classifier: Topic :: Text Processing :: Markup :: Markdown
Requires-Python: >=3.9
License-File: LICENSE.md
Requires-Dist: Markdown>=3.3.3
Provides-Extra: dev
Requires-Dist: pytest>=7.0.0; extra == "dev"
Requires-Dist: ruff>=0.1.0; extra == "dev"
